movie_quote_randomizer-0.1.0b7.dist-info/licenses/LICENSE
mq_randomizer/__about__.py
mq_randomizer/__init__.py
mq_randomizer/json_validation.py
mq_randomizer/pkg_resources.py
mq_randomizer/py.typed
mq_randomizer/quote_types.py
mq_randomizer/randomizer.py
mq_randomizer/version.py
mq_randomizer/data/__init__.py
mq_randomizer/data/hackers_quotes.json
mq_randomizer/data/quotes_schema.json
movie_quote_randomizer-0.1.0b7.dist-info/METADATA
movie_quote_randomizer-0.1.0b7.dist-info/WHEEL
movie_quote_randomizer-0.1.0b7.dist-info/top_level.txt
movie_quote_randomizer-0.1.0b7.dist-info/RECORD
