Metadata-Version: 2.4
Name: movie-quote-randomizer
Version: 0.1.0b7
Summary: A Python API to randomly select quotes from your favorite movie, TV show, video game, or whatever medium suits your fancy.
Home-page: https://github.com/zcutlip/movie-quote-randomizer
Author: Zachary Cutlip
Author-email: uid000@gmail.com
License: MIT
Classifier: Programming Language :: Python :: 3
Classifier: Programming Language :: Python :: 3.10
Classifier: Programming Language :: Python :: 3.11
Classifier: Programming Language :: Python :: 3.12
Classifier: Programming Language :: Python :: 3.13
Classifier: Operating System :: OS Independent
Classifier: Topic :: Software Development :: Libraries
Classifier: Topic :: Utilities
Requires-Python: >=3.10
License-File: LICENSE
Dynamic: author
Dynamic: author-email
Dynamic: classifier
Dynamic: description
Dynamic: description-content-type
Dynamic: home-page
Dynamic: license
Dynamic: license-file
Dynamic: requires-python
Dynamic: summary
